{
  "project_info": {
    "project_number": "805991309785",
    "project_id": "my-make-it-project",
    "storage_bucket": "my-make-it-project.firebasestorage.app"
  },
  "client": [
    {
      "client_info": {
        "mobilesdk_app_id": "1:805991309785:android:573df4f97dcbde1b3f39c8",
        "android_client_info": {
          "package_name": "com.example.makeitso"
        }
      },
      "oauth_client": [],
      "api_key": [
        {
          "current_key": "AIzaSyCIwNm_ZGIIiIWFwk3Kiebf-Jz33oBEjRM"
        }
      ],
      "services": {
        "appinvite_service": {
          "other_platform_oauth_client": []
        }
      }
    }
  ],
  "configuration_version": "1"
}